uvicorn_ssl_restarter/__init__.py
uvicorn_ssl_restarter/py.typed
uvicorn_ssl_restarter-0.1.4.dist-info/METADATA
uvicorn_ssl_restarter-0.1.4.dist-info/WHEEL
uvicorn_ssl_restarter-0.1.4.dist-info/RECORD
