Metadata-Version: 2.3
Name: uvicorn-ssl-restarter
Version: 0.1.4
Summary: Add your description here
Requires-Python: >=3.9
Requires-Dist: loguru>=0.7.2
Requires-Dist: pyopenssl>=24.2.1
Requires-Dist: uvicorn>=0.31.1
